[
  {
    "first_name": "Jameelah",
    "last_name": "Carver",
    "city": "Los Angeles",
    "state": "CA",
    "zip": "90094",
    "phone": "206-802-8426",
    "email": "jameelah.carver@artofliving.org"
  },
  {
    "first_name": "Saba",
    "last_name": "Chaudhary",
    "city": "Los Angeles",
    "state": "CA",
    "zip": "90036",
    "phone": "213-675-4188",
    "email": "sabac@artofliving.org"
  },
  {
    "first_name": "Madhu",
    "last_name": "Chidurala",
    "city": "Los Altos",
    "state": "CA",
    "zip": "94024",
    "phone": "408-483-3868",
    "email": "madhu.chidurala@artofliving.org"
  },
  {
    "first_name": "Prashanthi",
    "last_name": "Chidurala",
    "city": "Los Altos",
    "state": "CA",
    "zip": "94024",
    "phone": "408-709-0395",
    "email": "Prashanthic@artofliving.org"
  },
  {
    "first_name": "Anna",
    "last_name": "Chigogidze",
    "city": "Los Angeles",
    "state": "CA",
    "zip": "90007",
    "phone": "213-574-6417",
    "email": "anna.chigo@artofliving.org"
  },
  {
    "first_name": "Harshitha",
    "last_name": "Gopinathan",
    "city": "Irvine",
    "state": "CA",
    "zip": "92612",
    "phone": "732-351-5247",
    "email": "harshithag@artofliving.org"
  },
  {
    "first_name": "Deirdre",
    "last_name": "Jackson",
    "city": "Los Angeles",
    "state": "CA",
    "zip": "90007",
    "phone": "818-518-5106",
    "email": "deirdre.jackson@artofliving.org"
  },
  {
    "first_name": "Seema",
    "last_name": "Jain",
    "city": "Rancho Cucamonga",
    "state": "CA",
    "zip": "91739",
    "phone": "9092928874",
    "email": "seema.jain@artofliving.org"
  },
  {
    "first_name": "Ting-fen",
    "last_name": "Lin",
    "city": "Fresno",
    "state": "CA",
    "zip": "93619",
    "phone": "408-623-4972",
    "email": "tingfen.lin@artofliving.org"
  },
  {
    "first_name": "Shiva",
    "last_name": "Samudrala",
    "city": "San Deigo",
    "state": "CA",
    "zip": "92101",
    "phone": "612-817-2620",
    "email": "shivas@artofliving.org"
  },
  {
    "first_name": "Josette",
    "last_name": "Aggarwal",
    "city": "Los Angeles",
    "state": "CA",
    "zip": "94044",
    "phone": "310-951-1353",
    "email": "josette.aggarwal@artofliving.org"
  },
  {
    "first_name": "Sneha",
    "last_name": "Bandhawakar",
    "city": "Powell",
    "state": "OH",
    "zip": "43065",
    "phone": "612-868-3911",
    "email": "Snehab@artofliving.org"
  },
  {
    "first_name": "Pooja",
    "last_name": "Bhalode",
    "city": "Rochester",
    "state": "NY",
    "zip": "14467",
    "phone": "4129615783",
    "email": "pooja.bhalode@artofliving.org"
  },
  {
    "first_name": "Pam",
    "last_name": "Brockman",
    "city": "Washington",
    "state": "IL",
    "zip": "61571",
    "phone": "847-903-9674",
    "email": "pam.brockman@artofliving.org"
  },
  {
    "first_name": "Chetna",
    "last_name": "Cariappa",
    "city": "Greenbrook NJ",
    "state": "NJ",
    "zip": "08812",
    "phone": "908-510-0311",
    "email": "Chetna.Cariappa@artofliving.org"
  },
  {
    "first_name": "Ankit",
    "last_name": "Desai",
    "city": "Princeton, Florence (South Jersey)",
    "state": "NJ",
    "zip": "08518",
    "phone": "609-462-7583",
    "email": "ankit.desai@artofliving.org"
  },
  {
    "first_name": "Dhaneswori (Dhan)",
    "last_name": "Goboori",
    "city": "Asbury Park",
    "state": "NJ",
    "zip": "07712",
    "phone": "732-822-1428",
    "email": "dhan.goboori@artofliving.org"
  },
  {
    "first_name": "Padma",
    "last_name": "Gopalkrishna",
    "city": "Florance",
    "state": "KY",
    "zip": "41042",
    "phone": "224-633-6180",
    "email": "padma.gopal@artofliving.org"
  },
  {
    "first_name": "Nidhi",
    "last_name": "Gupta",
    "city": "Columbus",
    "state": "OH",
    "zip": "43064",
    "phone": "425-533-8514",
    "email": "Nidhi.gupta@artofliving.org"
  },
  {
    "first_name": "Sarita",
    "last_name": "Hardas",
    "city": "Eden Prairie,",
    "state": "MN",
    "zip": "55347",
    "phone": "859-913-2018",
    "email": "Sarita.hardas@artofliving.org"
  },
  {
    "first_name": "William",
    "last_name": "Herman",
    "city": "Chicago",
    "state": "IL",
    "zip": "60622",
    "phone": "312-421-0206",
    "email": "bill.herman@artofliving.org"
  },
  {
    "first_name": "Jennifer",
    "last_name": "Ka",
    "city": "Matawan",
    "state": "NJ",
    "zip": "07747",
    "phone": "562-637-3005",
    "email": "jennifer.ka@artofliving.org"
  },
  {
    "first_name": "Shenaz",
    "last_name": "Kapasi",
    "city": "Bronx",
    "state": "NY",
    "zip": "10468",
    "phone": "7183141239",
    "email": "Shenaz.kapasi@artofliving.org"
  },
  {
    "first_name": "Abhay",
    "last_name": "Ladhe",
    "city": "Minneapolis",
    "state": "MN",
    "zip": "55347",
    "phone": "859-684-5359",
    "email": "abhay.ladhe@artofliving.org"
  },
  {
    "first_name": "Latika",
    "last_name": "Menon",
    "city": "Boston",
    "state": "MA",
    "zip": "02118",
    "phone": "339-224-2787",
    "email": "Latika.menon@artofliving.org"
  },
  {
    "first_name": "Hitesh",
    "last_name": "Monga",
    "city": "",
    "state": "NH",
    "zip": "03031",
    "phone": "201-795-2131",
    "email": "hitesh.monga@artofliving.org"
  },
  {
    "first_name": "Shrivatsav",
    "last_name": "Pattabiraman",
    "city": "Boston",
    "state": "MA",
    "zip": "01536",
    "phone": "607-229-2700",
    "email": "shrip@artofliving.org"
  },
  {
    "first_name": "Uma",
    "last_name": "Raavi",
    "city": "Kendall park",
    "state": "NJ",
    "zip": "08824",
    "phone": "908-340-8201",
    "email": "uma.raavi@artofliving.org"
  },
  {
    "first_name": "Usha",
    "last_name": "Radhakrishnan",
    "city": "Minneapolis",
    "state": "MN",
    "zip": "55347",
    "phone": "952-215-6334",
    "email": "usha.radhakrishnan@artofliving.org"
  },
  {
    "first_name": "Gopika",
    "last_name": "Radhakrishnan",
    "city": "New Providence",
    "state": "NJ",
    "zip": "07974",
    "phone": "908-403-7429",
    "email": "gopika.rkrishnan@artofliving.org"
  },
  {
    "first_name": "Aparna",
    "last_name": "Ramanan",
    "city": "Brooklyn",
    "state": "NY",
    "zip": "95120",
    "phone": "202-429-7818",
    "email": "aparna.ramanan@artofliving.org"
  },
  {
    "first_name": "Pooja",
    "last_name": "Sarna",
    "city": "West Babylon, Long Island",
    "state": "NY",
    "zip": "11704",
    "phone": "6316819309",
    "email": "pooja.prakash@artofliving.org"
  },
  {
    "first_name": "Sumathi",
    "last_name": "Satish",
    "city": "North Brunswick",
    "state": "NJ",
    "zip": "08902",
    "phone": "732-322-5220",
    "email": "sumathi.satish@artofliving.org"
  },
  {
    "first_name": "Bidisha",
    "last_name": "Sen",
    "city": "Princeton",
    "state": "NJ",
    "zip": "08540",
    "phone": "6096138672",
    "email": "bidisha.sen@artofliving.org"
  },
  {
    "first_name": "Khevna",
    "last_name": "Shastri",
    "city": "Morris Plains",
    "state": "NJ",
    "zip": "07950",
    "phone": "440-339-3431",
    "email": "khevna.shastri@artofliving.org"
  },
  {
    "first_name": "Carla",
    "last_name": "Shohet",
    "city": "New York",
    "state": "NY",
    "zip": "10001",
    "phone": "646-267-5858",
    "email": "carla.shohet@artofliving.org"
  },
  {
    "first_name": "Kavishwar",
    "last_name": "Wagholikar",
    "city": "Grafton",
    "state": "MA",
    "zip": "01536",
    "phone": "347-574-4291",
    "email": "Kavishwarw@artofliving.org"
  },
  {
    "first_name": "Toshiyanka",
    "last_name": "Goswami",
    "city": "Beaverton",
    "state": "OR",
    "zip": "97003",
    "phone": "480-527-3219",
    "email": "tgoswami@artofliving.org"
  },
  {
    "first_name": "Gauri",
    "last_name": "Jinu",
    "city": "St Louis",
    "state": "MO",
    "zip": "63005",
    "phone": "3149394446",
    "email": "gauri.jinu@artofliving.org"
  },
  {
    "first_name": "Chella Kiruthiga",
    "last_name": "Kumar",
    "city": "Bothell",
    "state": "WA",
    "zip": "98012",
    "phone": "425-321-0986",
    "email": "chella.kumar@artofliving.org"
  },
  {
    "first_name": "Anjali",
    "last_name": "Pradeep Kumar",
    "city": "Portland",
    "state": "OR",
    "zip": "97229",
    "phone": "971-716-4581",
    "email": "anjali.pradeep@artofliving.org"
  },
  {
    "first_name": "Madhu",
    "last_name": "Rajanna",
    "city": "Bellevue",
    "state": "WA",
    "zip": "98007",
    "phone": "760-960-0862",
    "email": "madhu.rajanna@artofliving.org"
  },
  {
    "first_name": "Pranav Kumar",
    "last_name": "Suri",
    "city": "Boise",
    "state": "ID",
    "zip": "83716",
    "phone": "952-290-6787",
    "email": "Pranav.suri@artofliving.org"
  },
  {
    "first_name": "Nalini",
    "last_name": "Vardham",
    "city": "Pleasanton",
    "state": "CA",
    "zip": "94566",
    "phone": "408-601-9881",
    "email": "nalini.vardham@artofliving.org"
  },
  {
    "first_name": "Pavani",
    "last_name": "Yadlapati",
    "city": "Seattle",
    "state": "WA",
    "zip": "98074",
    "phone": "3032506648",
    "email": "Pavani.yadlapati@artofliving.org"
  },
  {
    "first_name": "Shashirekha",
    "last_name": "Alur",
    "city": "West San Jose",
    "state": "CA",
    "zip": "95129",
    "phone": "408-464-1013",
    "email": "Rekha.alur@artofliving.org"
  },
  {
    "first_name": "Aparna",
    "last_name": "Atmaram",
    "city": "Fremont",
    "state": "CA",
    "zip": "94536",
    "phone": "408-515-2360",
    "email": "aparna.atmaram@artofliving.org"
  },
  {
    "first_name": "Ruchi",
    "last_name": "Chand",
    "city": "San Jose",
    "state": "CA",
    "zip": "95129",
    "phone": "6506468211",
    "email": "ruchi.chand@artofliving.org"
  },
  {
    "first_name": "Nitisha",
    "last_name": "Gilra",
    "city": "Folsom",
    "state": "CA",
    "zip": "95742",
    "phone": "916-365-3753",
    "email": "nitisha.gilra@artofliving.org"
  },
  {
    "first_name": "Jeff",
    "last_name": "Knepper",
    "city": "Playa Vista",
    "state": "CA",
    "zip": "90094",
    "phone": "310-467-4009",
    "email": "jeff.knepper@artofliving.org"
  },
  {
    "first_name": "Neelam",
    "last_name": "Madaik",
    "city": "Boone",
    "state": "NC",
    "zip": "28607",
    "phone": "408-598-2557",
    "email": "neelam.madaik@artofliving.org"
  },
  {
    "first_name": "Elaavanya",
    "last_name": "Manoharan",
    "city": "Dublin",
    "state": "CA",
    "zip": "94568",
    "phone": "408-616-0424",
    "email": "Elaavanyam@artofliving.org"
  },
  {
    "first_name": "Aruna",
    "last_name": "Mantripragada",
    "city": "Fremont",
    "state": "CA",
    "zip": "94555",
    "phone": "510-648-1381",
    "email": "arunam@artofliving.org"
  },
  {
    "first_name": "Priya",
    "last_name": "Mayureshwar",
    "city": "Santa Clara",
    "state": "CA",
    "zip": "95054",
    "phone": "408-418-4964",
    "email": "priya.mayur@artofliving.org"
  },
  {
    "first_name": "Sowmya",
    "last_name": "Moily",
    "city": "Sunnyvale/Evergreen",
    "state": "CA",
    "zip": "94085",
    "phone": "9063702371",
    "email": "sowmya.moily@artofliving.org"
  },
  {
    "first_name": "Radhika",
    "last_name": "Narayan",
    "city": "Folsom",
    "state": "CA",
    "zip": "95630",
    "phone": "510-396-3880",
    "email": "radhika.narayan@artofliving.org"
  },
  {
    "first_name": "Bavani",
    "last_name": "Ramanan",
    "city": "Oakland",
    "state": "CA",
    "zip": "95120",
    "phone": "408-644-7356",
    "email": "bavani.ramanan@artofliving.org"
  },
  {
    "first_name": "Kanchana",
    "last_name": "Tatipigari",
    "city": "Folsom",
    "state": "CA",
    "zip": "95630",
    "phone": "916-983-9934",
    "email": "kanchana.tatipigari@artofliving.org"
  },
  {
    "first_name": "Vanitha",
    "last_name": "Thulasiraman",
    "city": "San Jose",
    "state": "CA",
    "zip": "95135",
    "phone": "408-387-2450",
    "email": "vanithat@artofliving.org"
  },
  {
    "first_name": "Anjali",
    "last_name": "Vishwanath",
    "city": "Palo Alto",
    "state": "CA",
    "zip": "94306",
    "phone": "650-812-0234",
    "email": "anjaliv@artofliving.org"
  },
  {
    "first_name": "Jiazhen",
    "last_name": "Zhang",
    "city": "San Francisco",
    "state": "CA",
    "zip": "94121",
    "phone": "4154202673",
    "email": "Jiazhen.zhang@artofliving.org"
  },
  {
    "first_name": "Gayatri",
    "last_name": "Mani",
    "city": "Rockville",
    "state": "MD",
    "zip": "20853",
    "phone": "301-461-3220",
    "email": "gayatri@iahv.org"
  },
  {
    "first_name": "Niru",
    "last_name": "Rajagopal",
    "city": "Austin",
    "state": "TX",
    "zip": "78728",
    "phone": "512-983-3637",
    "email": "niru.rajagopal@artofliving.org"
  },
  {
    "first_name": "Mamta",
    "last_name": "Bajaj",
    "city": "Davie",
    "state": "FL",
    "zip": "33325",
    "phone": "732-570-0628",
    "email": "mamta.bajaj@artofliving.org"
  },
  {
    "first_name": "Sridhar",
    "last_name": "Bandaru",
    "city": "Frisco",
    "state": "TX",
    "zip": "75034",
    "phone": "716-348-9798",
    "email": "sridhar.bandaru@artofliving.org"
  },
  {
    "first_name": "Pratibha",
    "last_name": "Chhabra",
    "city": "Fairfax",
    "state": "VA",
    "zip": "22032",
    "phone": "202-569-3793",
    "email": "pratibha.chhabra@artofliving.org"
  },
  {
    "first_name": "Keya",
    "last_name": "Chowdhury",
    "city": "Austin",
    "state": "TX",
    "zip": "78754",
    "phone": "713-384-5994",
    "email": "keyac@artofliving.org"
  },
  {
    "first_name": "Denise",
    "last_name": "Everheart",
    "city": "Royal Oak",
    "state": "MI",
    "zip": "48067",
    "phone": "248-705-5004",
    "email": "denise.everheart@artofliving.org"
  },
  {
    "first_name": "Tila",
    "last_name": "Foss",
    "city": "Fort Worth",
    "state": "TX",
    "zip": "76132",
    "phone": "682-235-8759",
    "email": "tila.foss@artofliving.org"
  },
  {
    "first_name": "Shyam",
    "last_name": "Gannavaram",
    "city": "Boone",
    "state": "NC",
    "zip": "28607",
    "phone": "503-724-7760",
    "email": "shyamg@artofliving.org"
  },
  {
    "first_name": "Elan",
    "last_name": "Gepner-Dales",
    "city": "Philadelphia",
    "state": "PA",
    "zip": "19144",
    "phone": "610-733-1101",
    "email": "elan.gepner@artofliving.org"
  },
  {
    "first_name": "Venkata Sudhakar",
    "last_name": "Haridasu",
    "city": "Fort Worth",
    "state": "TX",
    "zip": "76123",
    "phone": "214-772-1591",
    "email": "sudhakarhv@artofliving.org"
  },
  {
    "first_name": "Sriram",
    "last_name": "Iyer",
    "city": "Marietta",
    "state": "GA",
    "zip": "30066",
    "phone": "678-525-1769",
    "email": "sriram.iyer@artofliving.org"
  },
  {
    "first_name": "Shraddha",
    "last_name": "Iyer",
    "city": "Austin",
    "state": "TX",
    "zip": "78739",
    "phone": "512-522-1008",
    "email": "Shraddha.iyer@artofliving.org"
  },
  {
    "first_name": "Emin",
    "last_name": "Izzat",
    "city": "Newark",
    "state": "DE",
    "zip": "19711",
    "phone": "305-742-1517",
    "email": "emin.izzat@artofliving.org"
  },
  {
    "first_name": "Rajesh",
    "last_name": "Jethwani",
    "city": "Nashville",
    "state": "TN",
    "zip": "37221",
    "phone": "615-300-6034",
    "email": "Rajesh.Jethwani@artofliving.org"
  },
  {
    "first_name": "Anuradha",
    "last_name": "Jog",
    "city": "Cumming",
    "state": "GA",
    "zip": "30041",
    "phone": "470-309-6655",
    "email": "anuradha.jog@artofliving.org"
  },
  {
    "first_name": "Kiranmayi",
    "last_name": "K",
    "city": "Herndon",
    "state": "VA",
    "zip": "20171",
    "phone": "240-447-0204",
    "email": "kiranmayik@artofliving.org"
  },
  {
    "first_name": "Bhargavi",
    "last_name": "Kasam",
    "city": "Austin",
    "state": "TX",
    "zip": "78753",
    "phone": "512-853-0266",
    "email": "bhargavi.kasam@artofliving.org"
  },
  {
    "first_name": "Zafar",
    "last_name": "Khan",
    "city": "Washington",
    "state": "DC",
    "zip": "20009",
    "phone": "202-812-2529",
    "email": "zafar.khan@artofliving.org"
  },
  {
    "first_name": "Satya",
    "last_name": "Komirisetti",
    "city": "Austin",
    "state": "TX",
    "zip": "78681",
    "phone": "512-828-7218",
    "email": "satyak@artofliving.org"
  },
  {
    "first_name": "Lan",
    "last_name": "Lan",
    "city": "Edgewater",
    "state": "NJ",
    "zip": "07020",
    "phone": "201-375-1304",
    "email": "lan.lan@artofliving.org"
  },
  {
    "first_name": "Hong-Mei",
    "last_name": "Li",
    "city": "Philadelphia",
    "state": "PA",
    "zip": "19104",
    "phone": "267-702-5335  or  215-828-6478",
    "email": "Hong-Mei.li@artofliving.org"
  },
  {
    "first_name": "Shweta",
    "last_name": "Mahajan",
    "city": "Morrisville",
    "state": "NC",
    "zip": "27560",
    "phone": "570-540-6598",
    "email": "shweta.mahajan@artofliving.org"
  },
  {
    "first_name": "Sushma",
    "last_name": "Medikayala",
    "city": "Cary",
    "state": "NC",
    "zip": "27513",
    "phone": "910-674-7846",
    "email": "sushmam@artofliving.org"
  },
  {
    "first_name": "Mrinalini",
    "last_name": "Meesala",
    "city": "Lancaster",
    "state": "PA",
    "zip": "17603",
    "phone": "717-826-1560",
    "email": "mrinal.meesala@artofliving.org"
  },
  {
    "first_name": "Kritika",
    "last_name": "Nagpal",
    "city": "Atlanta",
    "state": "GA",
    "zip": "30080",
    "phone": "980-833-3503",
    "email": "Kritika.nagpal@artofliving.org"
  },
  {
    "first_name": "Shyama",
    "last_name": "Nair",
    "city": "Tampa",
    "state": "FL",
    "zip": "33617",
    "phone": "5617026236",
    "email": "shyama.nair@artofliving.org"
  },
  {
    "first_name": "Divija",
    "last_name": "Odapally",
    "city": "Houston",
    "state": "TX",
    "zip": "77407",
    "phone": "832-955-6273",
    "email": "divija.odapally@artofliving.org"
  },
  {
    "first_name": "Vaishnavi",
    "last_name": "Palaparty",
    "city": "Concord",
    "state": "NC",
    "zip": "28027",
    "phone": "647-287-4113",
    "email": "vaishnavi.palaparty@artofliving.org"
  },
  {
    "first_name": "Paresh",
    "last_name": "Parikh",
    "city": "Kannapolis",
    "state": "NC",
    "zip": "28081",
    "phone": "704-490-9074",
    "email": "paresh.parikh@artofliving.org"
  },
  {
    "first_name": "Falguni",
    "last_name": "Patel",
    "city": "Tampa",
    "state": "FL",
    "zip": "33578",
    "phone": "6023262828",
    "email": "Falguni.patel@artofliving.org"
  },
  {
    "first_name": "Jalpa",
    "last_name": "Patel",
    "city": "Derwood",
    "state": "MD",
    "zip": "20855",
    "phone": "571-528-9569",
    "email": "Jalpa.patel@artofliving.org"
  },
  {
    "first_name": "Sudha",
    "last_name": "Peri",
    "city": "Clarksburg",
    "state": "MD",
    "zip": "20871",
    "phone": "240-308-9520",
    "email": "sudha.peri@artofliving.org"
  },
  {
    "first_name": "Deepak",
    "last_name": "Ramrakhyani",
    "city": "Cocoa Beach",
    "state": "FL",
    "zip": "32931",
    "phone": "908-338-1007",
    "email": "deepak.ramrakhyani@artofliving.org"
  },
  {
    "first_name": "Somya",
    "last_name": "Ramrakhyani",
    "city": "Cocoa Beach",
    "state": "FL",
    "zip": "32931",
    "phone": "973-400-9191",
    "email": "somya.ramrakhyani@artofliving.org"
  },
  {
    "first_name": "Marlene",
    "last_name": "Sandhu",
    "city": "Falls Church",
    "state": "VA",
    "zip": "22043",
    "phone": "703.790.6152",
    "email": "marlene.sandhu@artofliving.org"
  },
  {
    "first_name": "Sejal",
    "last_name": "Shah",
    "city": "Boone",
    "state": "NC",
    "zip": "28607",
    "phone": "909 645 7103",
    "email": "Sejal.shah@artofliving.org"
  },
  {
    "first_name": "Mona",
    "last_name": "Shah-Joshi",
    "city": "Scottsdale",
    "state": "AZ",
    "zip": "30066",
    "phone": "678-595-7248",
    "email": "madhurina@artofliving.org"
  },
  {
    "first_name": "Poornima",
    "last_name": "Sharma",
    "city": "Boone",
    "state": "NC",
    "zip": "28607",
    "phone": "503-724-7742",
    "email": "poornima.sharma@artofliving.org"
  },
  {
    "first_name": "Simi",
    "last_name": "Sharma Parashar",
    "city": "Plano",
    "state": "TX",
    "zip": "75024",
    "phone": "469-969-8771",
    "email": "simi.sharma@artofliving.org"
  },
  {
    "first_name": "Run",
    "last_name": "Singh",
    "city": "Uvalde",
    "state": "TX",
    "zip": "",
    "phone": "",
    "email": "runsingh@gmail.com"
  },
  {
    "first_name": "Vibha",
    "last_name": "Sood",
    "city": "Flower Mound",
    "state": "TX",
    "zip": "75028",
    "phone": "972-965-2296",
    "email": "vibha.sood@artofliving.org"
  },
  {
    "first_name": "Katie",
    "last_name": "Tomer",
    "city": "Charlotte",
    "state": "NC",
    "zip": "28262",
    "phone": "856-466-5596",
    "email": "katie.tomer@artofliving.org"
  },
  {
    "first_name": "Hetal",
    "last_name": "Varia",
    "city": "Houston",
    "state": "TX",
    "zip": "77407",
    "phone": "203-243-9965",
    "email": "hetal.varia@artofliving.org"
  },
  {
    "first_name": "Usha",
    "last_name": "Venkatachalam",
    "city": "Marietta",
    "state": "GA",
    "zip": "30062",
    "phone": "770-541-7679",
    "email": "ushav@artofliving.org"
  },
  {
    "first_name": "Angela",
    "last_name": "Warner",
    "city": "Monument",
    "state": "CO",
    "zip": "80132",
    "phone": "719-651-4129",
    "email": "angela.warner@artofliving.org"
  },
  {
    "first_name": "Nancy",
    "last_name": "Zalazar",
    "city": "Los Angeles",
    "state": "CA",
    "zip": "90008",
    "phone": "832-609-0156",
    "email": "nancy.zalazar@artofliving.org"
  },
  {
    "first_name": "Kishore Kumar",
    "last_name": "Kadari",
    "city": "Pinellas Park",
    "state": "FL",
    "zip": "33782",
    "phone": "813-585-2392",
    "email": "kishore.kadari@artofliving.org"
  }
]